switch_config_render/__init__.py
switch_config_render/__main__.py
switch_config_render/canvas.py
switch_config_render/generate_svg.py
switch_config_render/utils.py
switch_config_render/_examples/__init__.py
switch_config_render/_examples/high_level_example.py
switch_config_render/_examples/low_level_example.py
switch_config_render-0.2.1.dist-info/DESCRIPTION.rst
switch_config_render-0.2.1.dist-info/METADATA
switch_config_render-0.2.1.dist-info/RECORD
switch_config_render-0.2.1.dist-info/WHEEL
switch_config_render-0.2.1.dist-info/metadata.json
switch_config_render-0.2.1.dist-info/top_level.txt
